{
  "VahidOOnLine": 243271,
  "mwarmonitor": 10003,
  "pm_afshaa": 92060,
  "iaghapour": 2649,
  "DEJradio": 5231,
  "mamlekate": 103605,
  "VahidOnline": 75856,
  "kianmeli1": 87685,
  "IranIntlTV": 340101,
  "FoxNewsChannel": 3,
  "Shin_Persian": 6373,
  "Iliaen": 4437,
  "CnnBrk": 247615,
  "reutersworldchannel": 151527,
  "ManotoTV": 105898,
  "FarsiVOA": 219305,
  "DW_Farsi": 125394,
  "Persian_Trend_Official": 15453,
  "RadioFarda": 157787,
  "IranianMinds": 21207,
  "BBCPersian": 282591,
  "IranWire": 65,
  "idfinfarsi": 11704,
  "Dirty_Kids": 390770,
  "Hranews": 113313,
  "officialrezapahlavi": 1835,
  "configx2ray": 38663,
  "manototv": 105898,
  "alonews": 124299,
  "farsi_fox_news": 89200,
  "FoxNewsTwitter": 342478,
  "CNNfarsiCHANNEL": 51273,
  "WithYashar": 13190
}