{
  "VahidOOnLine": 243279,
  "mwarmonitor": 10007,
  "pm_afshaa": 92069,
  "iaghapour": 2649,
  "DEJradio": 5233,
  "mamlekate": 103605,
  "VahidOnline": 75861,
  "kianmeli1": 87685,
  "IranIntlTV": 340111,
  "FoxNewsChannel": 3,
  "Shin_Persian": 6375,
  "Iliaen": 4437,
  "CnnBrk": 247615,
  "reutersworldchannel": 151527,
  "ManotoTV": 105898,
  "FarsiVOA": 219312,
  "DW_Farsi": 125397,
  "Persian_Trend_Official": 15458,
  "RadioFarda": 157790,
  "IranianMinds": 21213,
  "BBCPersian": 282595,
  "IranWire": 65,
  "idfinfarsi": 11704,
  "Dirty_Kids": 390778,
  "Hranews": 113315,
  "officialrezapahlavi": 1835,
  "configx2ray": 38663,
  "manototv": 105898,
  "alonews": 124318,
  "farsi_fox_news": 89200,
  "FoxNewsTwitter": 342481,
  "CNNfarsiCHANNEL": 51273,
  "WithYashar": 13205
}